Metadata-Version: 2.1
Name: serendipy
Version: 0.1.5
Summary: Bi-level optimization for gurobi
Home-page: UNKNOWN
Author: jqy
Author-email: jiaqiyuejqy@gmail.com
License: Apache2.0
Platform: UNKNOWN
Classifier: Programming Language :: Python
Classifier: Programming Language :: Python :: 3.6
